{
  "last_updated": "2025-10-05T18:53:44.695039",
  "total_articles": 3,
  "daily_articles": [
    {
      "date": "2025-10-05",
      "articles": [
        {
          "url": "https://cointelegraph.com/news/bitcoin-mining-difficulty-hits-record-high",
          "title": "Bitcoin Mining Difficulty Hits New Record High Following Network Upgrade",
          "description": "Bitcoin's mining difficulty has reached an all-time high as the network continues to strengthen its security infrastructure.",
          "source": "Cointelegraph",
          "dateTimePub": "2025-10-05T14:30:00Z",
          "fetched_at": "2025-10-05T18:53:44.695007",
          "posted_to_twitter": false,
          "queued_for_twitter": false,
          "lang": "eng",
          "isDuplicate": false,
          "wgt": 85
        },
        {
          "url": "https://bitcoinmagazine.com/business/marathon-digital-expands-mining-operations",
          "title": "Marathon Digital Announces Major Expansion of Mining Operations in Texas",
          "description": "Marathon Digital Holdings reveals plans to deploy 15,000 new ASIC miners across multiple facilities.",
          "source": "Bitcoin Magazine",
          "dateTimePub": "2025-10-05T12:15:00Z",
          "fetched_at": "2025-10-05T18:53:44.695015",
          "posted_to_twitter": false,
          "queued_for_twitter": false,
          "lang": "eng",
          "isDuplicate": false,
          "wgt": 92
        },
        {
          "url": "https://decrypt.co/news/renewable-energy-bitcoin-mining-growth",
          "title": "Renewable Energy Powers 60% of Bitcoin Mining Operations, Study Shows",
          "description": "New research indicates a significant shift toward sustainable energy sources in Bitcoin mining.",
          "source": "Decrypt",
          "dateTimePub": "2025-10-05T10:45:00Z",
          "fetched_at": "2025-10-05T18:53:44.695019",
          "posted_to_twitter": false,
          "queued_for_twitter": false,
          "lang": "eng",
          "isDuplicate": false,
          "wgt": 78
        }
      ],
      "fetch_count": 1
    }
  ]
}